covid19_model/__init__.py
covid19_model/main.py
covid19_model/models.c
covid19_model/models.cpython-311-darwin.so
covid19_model/models.pyx
covid19_model/solver.c
covid19_model/solver.cpython-311-darwin.so
covid19_model/solver.pyx
covid19_model/visualizer.py
covid19_model-1.2.dist-info/LICENSE
covid19_model-1.2.dist-info/METADATA
covid19_model-1.2.dist-info/WHEEL
covid19_model-1.2.dist-info/top_level.txt
covid19_model-1.2.dist-info/RECORD
