Metadata-Version: 2.1
Name: covid19-model
Version: 1.2
Summary: A package including several compartmental models, that are solved and visualized based on real data
Author-email: Samuel Mulzer <samuel.mulzer@icloud.com>
Requires-Python: >=3.10
License-File: LICENSE
Requires-Dist: matplotlib (>=3.6.2)
Requires-Dist: numpy (>=1.23.5)
